bgym/__init__.py
browsergym/experiments/__init__.py
browsergym/experiments/agent.py
browsergym/experiments/loop.py
browsergym/experiments/utils.py
browsergym/experiments/benchmark/__init__.py
browsergym/experiments/benchmark/base.py
browsergym/experiments/benchmark/configs.py
browsergym/experiments/benchmark/utils.py
browsergym/experiments/benchmark/metadata/assistantbench.csv
browsergym/experiments/benchmark/metadata/miniwob.csv
browsergym/experiments/benchmark/metadata/scripts.py
browsergym/experiments/benchmark/metadata/utils.py
browsergym/experiments/benchmark/metadata/visualwebarena.csv
browsergym/experiments/benchmark/metadata/webarena.csv
browsergym/experiments/benchmark/metadata/webarena_verified.csv
browsergym/experiments/benchmark/metadata/webarenalite.csv
browsergym/experiments/benchmark/metadata/weblinx.csv
browsergym/experiments/benchmark/metadata/workarena.csv
browsergym_experiments-0.14.3.dist-info/METADATA
browsergym_experiments-0.14.3.dist-info/WHEEL
browsergym_experiments-0.14.3.dist-info/RECORD
